MANIFEST.in
setup.py
video_brain/__init__.py
video_brain.egg-info/PKG-INFO
video_brain.egg-info/SOURCES.txt
video_brain.egg-info/dependency_links.txt
video_brain.egg-info/not-zip-safe
video_brain.egg-info/top_level.txt
video_brain/graph_parser/__init__.py
video_brain/graph_parser/data_provider.py
video_brain/graph_parser/db_manager.py
video_brain/graph_parser/exceptions.py
video_brain/graph_parser/factory.py
video_brain/graph_parser/graph_browser.py
video_brain/graph_parser/image_processer.py
video_brain/graph_parser/interpreter.py
video_brain/graph_parser/motion.py
video_brain/graph_parser/network_evaluator.py
video_brain/graph_parser/network_trainer.py
video_brain/graph_parser/os_manager.py
video_brain/graph_parser/reporter.py
video_brain/graph_parser/sequence_input_layer.py
video_brain/graph_parser/settings.ini
video_brain/graph_parser/settings.py
video_brain/graph_parser/utils.py
video_brain/graph_parser/visualizator.py
video_brain/graph_parser/tests/__init__.py
video_brain/graph_parser/tests/factory.py
video_brain/graph_parser/tests/graph_browser.py
video_brain/graph_parser/tests/interpreter.py
video_brain/graph_parser/tests/network_evaluator.py
video_brain/graph_parser/tests/visualize.py
video_brain/resources/onto.graphml
video_brain/resources/motion/deploy_lstm.prototxt
video_brain/resources/motion/extract_frames.sh
video_brain/resources/motion/labels.pkl
video_brain/resources/motion/weights.caffemodel
video_brain/resources/networks/alexnet/deploy.prototxt
video_brain/resources/networks/alexnet/solver.prototxt
video_brain/resources/networks/alexnet/train_val.prototxt
video_brain/resources/networks/alexnet/valnet.prototxt
video_brain/resources/networks/deep_residual/deploy.prototxt
video_brain/resources/networks/deep_residual/solver.prototxt
video_brain/resources/networks/deep_residual/train_val.prototxt
video_brain/resources/networks/deep_residual/valnet.prototxt
video_brain/resources/networks/deep_residual/weights.caffemodel
video_brain/resources/nlp/GoogleNews-vectors-negative300.bin
video_brain/resources/nlp/dictionary.pkl
video_brain/resources/tags_cnn/testnet.prototxt
video_brain/resources/themes/deploy.prototxt
