Metadata-Version: 1.0
Name: video-brain
Version: 0.1
Summary: Deep Learning for video processing tasks
Home-page: UNKNOWN
Author: Léo Vetter
Author-email: vetter.leo@gmail.com
License: MIT
Platform: UNKNOWN
